[{"TicketCost":"1","FightCardLowestTalentMod":0.6,"FightCardModifierAdjustment":0.17,"MovePercentMod":0.33,"Name":"The Streak","Difficulty":"The-Streak","Quests":[{"Name":"Jake The Snake","Type":"Single","QuestID":"1","SurvivalMatch":false,"Reward":{"ID":"SoftCurrency","Reward":"Coins","Amount":"25000","Type":"NormalCurrency","Slug":"softcurrency"}},{"Name":"Kevin Nash","Type":"Single","QuestID":"2","SurvivalMatch":false,"Reward":{"ID":"GachaShard_3Star_Case","Reward":"Headliner Chips","Amount":"1000","Type":"GachaToken","Slug":"gachashard-3star-case"}},{"Name":"Kane","Type":"Single","QuestID":"3","SurvivalMatch":false,"Reward":{"ID":"pvp_tp_bag_10","Reward":"Mystery 10 TP Bag","Amount":"1","Type":"BagToken","Slug":"pvp-tp-bag-10"}},{"Name":"Big Boss Man","Type":"Single","QuestID":"4","SurvivalMatch":false,"Reward":{"ID":"SoftCurrency","Reward":"Coins","Amount":"50000","Type":"NormalCurrency","Slug":"softcurrency"}},{"Name":"Ric Flair","Type":"Single","QuestID":"5","SurvivalMatch":false,"Reward":{"ID":"GachaShard_3Star_Case","Reward":"Headliner Chips","Amount":"2000","Type":"GachaToken","Slug":"gachashard-3star-case"}},{"Name":"Randy Orton","Type":"Single","QuestID":"6","SurvivalMatch":false,"Reward":{"ID":"pvp_tp_bag_25","Reward":"Mystery 25 TP Bag","Amount":"1","Type":"BagToken","Slug":"pvp-tp-bag-25"}},{"Name":"Batista","Type":"Single","QuestID":"7","SurvivalMatch":false,"Reward":{"ID":"SoftCurrency","Reward":"Coins","Amount":"100000","Type":"NormalCurrency","Slug":"softcurrency"}},{"Name":"Edge","Type":"Single","QuestID":"8","SurvivalMatch":false,"Reward":{"ID":"GachaShard_3Star_Case","Reward":"Headliner Chips","Amount":"6000","Type":"GachaToken","Slug":"gachashard-3star-case"}},{"Name":"Shawn Michaels","Type":"Single","QuestID":"9","SurvivalMatch":false,"Reward":{"ID":"pvp_tp_bag_50","Reward":"Mystery 50 TP Bag","Amount":"1","Type":"BagToken","Slug":"pvp-tp-bag-50"}},{"Name":"Brock Lesnar","Type":"Single","QuestID":"10","SurvivalMatch":false,"Reward":{"ID":"undertaker_tomb_silver_bag","Reward":"Kings of WrestleMania Collection Event Silver Undertaker Tomb","Amount":"1","Type":"BagToken","Slug":"undertaker-tomb-silver-bag"}}]}]